src/__init__.py
alpha_orm-0.0.111.dist-info/LICENSE
alpha_orm-0.0.111.dist-info/METADATA
alpha_orm-0.0.111.dist-info/WHEEL
alpha_orm-0.0.111.dist-info/top_level.txt
alpha_orm-0.0.111.dist-info/RECORD
