Metadata-Version: 2.1
Name: alpha-orm
Version: 0.0.111
Summary: A nice database orm written in python
Home-page: https://github.com/alpha-orm/python-alpha-orm
Author: Claret Nnamocha
Author-email: devclareo@gmail.com
License: UNKNOWN
Platform: UNKNOWN
Classifier: Programming Language :: Python :: 3
Classifier: License :: OSI Approved :: MIT License
Classifier: Operating System :: OS Independent
Requires-Python: >=3.6
